{
    "appTitle": "Hablas",
    "login": "Pripojiť",
    "signup": "Zapisovať",
    "dailyPages": "Denné stránky",
    "freeRead": "Čítanie zadarmo",
    "pleaseLoginToStart": "Pripojte sa k spusteniu",
    "email": "E-mail",
    "password": "Heslo",
    "settings": "Parametre",
    "switchToMode": "Ísť",
    "nativeLanguage": "Rodný jazyk",
    "tutorial": "Výučba",
    "supportHablas": "Podpora hablas",
    "foundABug": "Nájdite chybu",
    "sendingBugReport": "Odosielanie správy o Bogu ...",
    "bugReportSent": "Správa o chybe odoslaná! Ďakujeme, že ste nám pomohli zlepšiť sa.",
    "bugReportError": "Chyba odosielanie správy o chybe. Skúšam to znova.",
    "tapToBegin": "Stlačte sem a spustite!",
    "selectPagele": "Vyberte pagele",
    "chapters": "Kapitoly",
    "translate": "Preložiť",
    "loading": "Načítanie ...",
    "translating": "Preklad ...",
    "processing": "Liečba ...",
    "fetchingData": "Obnoviť údaje ...",
    "parsingData": "Analýza údajov ...",
    "loadMore": "Zaťažiť viac",
    "chapterTitle": "Názov kapitoly",
    "points": "Body",
    "prevSentence": "Predchádzajúci",
    "nextSentence": "Najbližší",
    "loggedInAs": "Pripojený ako",
    "logout": "Odpojenie",
    "changeInfo": "Upraviť informácie",
    "deleteAccount": "Vymazať účet",
    "userAccountOptions": "Možnosti používateľského účtu",
    "completeYourTip": "Dokončite svoju radu",
    "payNow": "Platiť",
    "customAmount": "Personalizovaná suma",
    "tip": "Poradiť",
    "thankYouForTip": "Ďakujeme za vašu radu!",
    "invalidCredentials": "NEVALIDOVÉ REFERENCIE, Riskovali ste sa?",
    "sessionExpired": "Vaša relácia vypršala. Znovu sa včelím.",
    "enterValidEmail": "Vložte platnú e -mailovú adresu",
    "passwordCannotBeEmpty": "Heslo nemôže byť prázdne",
    "microphonePermissionRequired": "Na registráciu je potrebné povolenie mikrofónu.",
    "couldNotAccessMicrophone": "Nemožno získať prístup k mikrofónu. Skontrolujte autorizácie vášho prehliadača.",
    "failedToStartRecording": "Nemohol začať nahrávať. Vyskúšajte znova.",
    "enterValidAmount": "Zadajte platnú sumu",
    "errorLoadingTutorial": "Obsah tutoriálu načítania chýb",
    "pleaseTryAgain": "Skúste to znova neskôr.",
    "noSentencesAvailable": "Pre túto kapitolu nie je k dispozícii žiadna veta.",
    "noChaptersAvailable": "Žiadna kapitola k dispozícii.",
    "noPageleBooksAvailable": "Nie sú k dispozícii žiadne knihy pagele.",
    "reachedEndOfBook": "Dosiahne koniec knihy",
    "errorRenderingBook": "Kniha",
    "errorProcessingTip": "Tip na ošetrenie chýb. Skúšajte znova."
}